{"completed": true, "created": 1421336753951, "dac_url": "http://54.91.88.156/deployment/54b7e0b1d248950ee6db55a1", "dap": "http://data.ioos.us/gliders/thredds/dodsC/deployments/rutgers/ud_134-20150105T1601/ud_134-20150105T1601.nc3.nc", "datasetID": "ud_134-20150105T1601", "east": -64.046825636582, "end": 1421862080000, "estimated_deploy_date": null, "estimated_deploy_location": null, "fgdc": "http://data.ioos.us/gliders/erddap/metadata/fgdc/xml/ud_134-20150105T1601_fgdc.xml", "graph": "http://data.ioos.us/gliders/erddap/tabledap/ud_134-20150105T1601.graph", "id": "54b7e0b1d248950ee6db55a1", "institution": "University of Delaware", "iso": "http://data.ioos.us/gliders/erddap/tabledap/ud_134-20150105T1601.iso19115", "meta": "http://data.ioos.us/gliders/erddap/info/ud_134-20150105T1601/index", "name": "ud_134-20150105T1601", "north": -64.81109059810689, "num_profiles": 416, "operator": "University of Delaware", "rss": "http://data.ioos.us/gliders/erddap/rss/ud_134-20150105T1601.rss", "sos": "http://data.ioos.us/gliders/thredds/sos/deployments/rutgers/ud_134-20150105T1601/ud_134-20150105T1601.nc3.nc?service=SOS&request=GetCapabilities&AcceptVersions=1.0.0", "south": -64.89351938615162, "start": 1420474170000, "status": null, "subset": "http://data.ioos.us/gliders/erddap/tabledap/ud_134-20150105T1601.subset", "summary": "The purpose of this glider mission is to do cross canyon transects of Palmer Deep within the operating CODAR fields off of Anvers Island.  This multi-platform field study will investigate the impact of coastal physical processes (e.g. tides, currents, upwelling events, sea-ice) on Ad\ufffd\ufffdlie penguin foraging ecology in the vicinity of Palmer Deep, off Anvers Island, WAP. Guided by real-time surface convergence and divergences based on remotely sensed surface current maps derived from a coastal network of High Frequency Radars (HFRs), a multidisciplinary research team will adaptively sample the distribution of phytoplankton and zooplankton, which influence Ad\ufffd\ufffdlie penguin foraging ecology, to understand how local oceanographic processes structure the ecosystem.", "tabledap": "http://data.ioos.us/gliders/erddap/tabledap/ud_134-20150105T1601", "tds": "http://data.ioos.us/gliders/thredds/dodsC/deployments/rutgers/ud_134-20150105T1601/catalog.html?dataset=deployments/rutgers/ud_134-20150105T1601/ud_134-20150105T1601.nc3.nc", "title": "ud_134-20150105T1601", "ts0": "2015-01-05T16:09:30Z", "ts1": "2015-01-21T17:41:20Z", "updated": 1423602390008, "username": "rutgers", "west": -64.307366250233, "wmo_id": "7801503"}